{
    "strengths": {
        "USD": 6.14,
        "EUR": 3.0,
        "GBP": 2.43,
        "JPY": 2.29,
        "AUD": 7.43,
        "NZD": 5.86,
        "CAD": 4.57,
        "CHF": 4.29
    },
    "gaps": {
        "EUR/USD": 3.14,
        "GBP/USD": 3.71,
        "USD/JPY": 3.86,
        "AUD/USD": 1.29,
        "NZD/USD": 0.29,
        "USD/CAD": 1.57,
        "USD/CHF": 1.86,
        "EUR/GBP": 0.57,
        "EUR/JPY": 0.71,
        "EUR/AUD": 4.43,
        "EUR/NZD": 2.86,
        "EUR/CAD": 1.57,
        "EUR/CHF": 1.29,
        "GBP/JPY": 0.14,
        "GBP/AUD": 5.0,
        "GBP/NZD": 3.43,
        "GBP/CAD": 2.14,
        "GBP/CHF": 1.86,
        "AUD/JPY": 5.14,
        "NZD/JPY": 3.57,
        "CAD/JPY": 2.29,
        "CHF/JPY": 2.0,
        "AUD/NZD": 1.57,
        "AUD/CAD": 2.86,
        "AUD/CHF": 3.14,
        "NZD/CAD": 1.29,
        "NZD/CHF": 1.57,
        "CAD/CHF": 0.29
    }
}